djangoldp_tamis/__init__.py
djangoldp_tamis/admin.py
djangoldp_tamis/apps.py
djangoldp_tamis/forms.py
djangoldp_tamis/settings.py
djangoldp_tamis/fixtures/sample_tamis_data.nt
djangoldp_tamis/fixtures/sample_tamis_data.ttl
djangoldp_tamis/fixtures/tamis_dashboard.json
djangoldp_tamis/fixtures/tamis_sample.json
djangoldp_tamis/migrations/0001_initial.py
djangoldp_tamis/migrations/0002_alter_prestationstep_prestation.py
djangoldp_tamis/migrations/0003_steptotemplate_validation_date.py
djangoldp_tamis/migrations/0004_rename_issuers_asset_issuer_and_more.py
djangoldp_tamis/migrations/0005_prestation_creator.py
djangoldp_tamis/migrations/0006_remove_prestationstep_prestation_prestation_steps_and_more.py
djangoldp_tamis/migrations/0007_tamisprofile.py
djangoldp_tamis/migrations/0008_alter_tamisprofile_options.py
djangoldp_tamis/migrations/0009_agent_creation_date_agent_update_date_and_more.py
djangoldp_tamis/migrations/0010_remove_asset_identifier_remove_asset_issuer_and_more.py
djangoldp_tamis/migrations/0011_remove_asset_identifiants_and_more.py
djangoldp_tamis/migrations/0012_commande_prestation_commande.py
djangoldp_tamis/migrations/0013_prestation_start_date.py
djangoldp_tamis/migrations/0014_prestation_type.py
djangoldp_tamis/migrations/0015_remove_prestation_devis_id.py
djangoldp_tamis/migrations/0016_remove_format_identifiants_format_identifier_and_more.py
djangoldp_tamis/migrations/0017_rename_name_editorialwork_title_and_more.py
djangoldp_tamis/migrations/0018_client_provider_remove_commande_client_name_and_more.py
djangoldp_tamis/migrations/__init__.py
djangoldp_tamis/models/__base.py
djangoldp_tamis/models/__init__.py
djangoldp_tamis/models/agent.py
djangoldp_tamis/models/asset.py
djangoldp_tamis/models/audio_track.py
djangoldp_tamis/models/client.py
djangoldp_tamis/models/commande.py
djangoldp_tamis/models/editorial_work.py
djangoldp_tamis/models/editorial_work_tag.py
djangoldp_tamis/models/favourite.py
djangoldp_tamis/models/format.py
djangoldp_tamis-1.1.3.dist-info/METADATA
djangoldp_tamis-1.1.3.dist-info/WHEEL
djangoldp_tamis-1.1.3.dist-info/top_level.txt
djangoldp_tamis-1.1.3.dist-info/RECORD
