Metadata-Version: 2.1
Name: djangoldp-tamis
Version: 1.1.3
Summary: djangoldp package for TAMIS
Home-page: https://git.startinblox.com/djangoldp-packages/djangoldp-tamis
Author: Startin'blox
Author-email: jbaptiste@startinblox.com
License: MIT
Classifier: Programming Language :: Python :: 3
Requires-Dist: djangoldp~=3.1.0
Requires-Dist: djangoldp-account~=3.1.0
Requires-Dist: djangoldp-dashboard~=3.0.0
Provides-Extra: include_package_data
Requires-Dist: True; extra == "include-package-data"
